celiagg/_celiagg.cpython-314-darwin.so
celiagg/__init__.py
celiagg/tests/test_transform.py
celiagg/tests/test_font.py
celiagg/tests/test_no_text.py
celiagg/tests/__init__.py
celiagg/tests/test_canvas.py
celiagg/tests/test_drawing.py
celiagg/tests/test_state.py
celiagg/tests/test_text.py
celiagg/tests/test_path.py
celiagg/tests/test_paint.py
celiagg/data/__init__.py
celiagg/data/OFL.txt
celiagg/data/Montserrat-Regular.ttf
celiagg-2.1.7.dist-info/RECORD
celiagg-2.1.7.dist-info/WHEEL
celiagg-2.1.7.dist-info/top_level.txt
celiagg-2.1.7.dist-info/METADATA
celiagg-2.1.7.dist-info/licenses/LICENSE
